qmesh
