Metadata-Version: 1.1
Name: qmesh
Version: 1.0.2
Summary: Finite Element meshes from GIS data.
Home-page: http://www.qmesh.org
Author: The QMesh Development Team.
Author-email: develop@qmesh.org
License: GPLv3
Download-URL: https://bitbucket.org/qmesh-developers/qmesh/commits/tag/1.0.0
Keywords: GIS,mesh generation
Platform: UNKNOWN
Provides: qmesh
